README.rst
setup.py
bin/members
members/__init__.py
members/_version.py
members/facebook_group.py
members/github_repo.py
members/mailman2.py
members/orgchart3.py
members/utils.py
members.egg-info/PKG-INFO
members.egg-info/SOURCES.txt
members.egg-info/dependency_links.txt
members.egg-info/not-zip-safe
members.egg-info/requires.txt
members.egg-info/top_level.txt