Metadata-Version: 1.1
Name: members
Version: 0.0.5
Summary: Get membership details from various data sources.
Home-page: https://github.com/kejbaly2/members
Author: Chris Ward
Author-email: cward@redhat.com
License: GPLv3
Download-URL: https://github.com/kejbaly2/members/archive/master.zip
Keywords: information
Platform: UNKNOWN
Classifier: License :: OSI Approved :: GNU General Public License v3 (GPLv3)
Classifier: Natural Language :: English
Classifier: Programming Language :: Python :: 2.7
Classifier: Topic :: Office/Business
Classifier: Topic :: Utilities
Provides: members
